tri_declarative/__init__.py
tri_declarative/declarative.py
tri_declarative/dispatch.py
tri_declarative/evaluate.py
tri_declarative/namespace.py
tri_declarative/refinable.py
tri_declarative/shortcut.py
tri_declarative/sort_after.py
tri_declarative/util.py
tri_declarative/with_meta.py
tri.declarative-5.7.0.dist-info/AUTHORS.rst
tri.declarative-5.7.0.dist-info/LICENSE
tri.declarative-5.7.0.dist-info/METADATA
tri.declarative-5.7.0.dist-info/WHEEL
tri.declarative-5.7.0.dist-info/top_level.txt
tri.declarative-5.7.0.dist-info/RECORD
