Metadata-Version: 1.1
Name: tri.declarative
Version: 5.7.0
Summary: tri.declarative contains class decorators to define classes with subclass semantics in the style of django Model classes.
Home-page: https://github.com/TriOptima/tri.declarative
Author: Johan Lübcke
Author-email: johan.lubcke@trioptima.com
License: BSD
Keywords: tri.declarative
Platform: UNKNOWN
Classifier: Development Status :: 4 - Beta
Classifier: Intended Audience :: Developers
Classifier: License :: OSI Approved :: BSD License
Classifier: Natural Language :: English
Classifier: Programming Language :: Python :: 3
Classifier: Programming Language :: Python :: 3.6
